graphite_feeder/__init__.py
graphite_feeder/__main__.py
graphite_feeder/conf/__init__.py
graphite_feeder/conf/logging.py
graphite_feeder/handler/__init__.py
graphite_feeder/handler/graph.py
graphite_feeder/handler/appliance/__init__.py
graphite_feeder/handler/appliance/handler.py
graphite_feeder/handler/appliance/registry.py
graphite_feeder/handler/appliance/curtain/__init__.py
graphite_feeder/handler/appliance/curtain/indoor/__init__.py
graphite_feeder/handler/appliance/curtain/indoor/blackout.py
graphite_feeder/handler/appliance/curtain/outdoor/__init__.py
graphite_feeder/handler/appliance/curtain/outdoor/bedroom.py
graphite_feeder/handler/appliance/light/__init__.py
graphite_feeder/handler/appliance/light/indoor/__init__.py
graphite_feeder/handler/appliance/light/indoor/dimmerable.py
graphite_feeder/handler/appliance/light/indoor/hue.py
graphite_feeder/handler/appliance/light/indoor/presence.py
graphite_feeder/handler/appliance/light/indoor/zone.py
graphite_feeder/handler/appliance/sensor/__init__.py
graphite_feeder/handler/appliance/sensor/alarm.py
graphite_feeder/handler/appliance/sensor/anemometer.py
graphite_feeder/handler/appliance/sensor/luxmeter.py
graphite_feeder/handler/appliance/sensor/motion.py
graphite_feeder/handler/appliance/sensor/powermeter.py
graphite_feeder/handler/appliance/sensor/rain.py
graphite_feeder/handler/appliance/sensor/scene.py
graphite_feeder/handler/appliance/sensor/thermometer.py
graphite_feeder/handler/appliance/socket/__init__.py
graphite_feeder/handler/appliance/socket/energy_guard.py
graphite_feeder/handler/appliance/socket/presence/__init__.py
graphite_feeder/handler/appliance/socket/presence/christmas.py
graphite_feeder/handler/appliance/sound/__init__.py
graphite_feeder/handler/appliance/sound/player.py
graphite_feeder/handler/appliance/sprinkler/__init__.py
graphite_feeder/handler/appliance/thermostat/__init__.py
graphite_feeder/handler/appliance/thermostat/presence.py
graphite_feeder/handler/event/__init__.py
automate_graphite_feeder-0.9.1.dist-info/COPYING
automate_graphite_feeder-0.9.1.dist-info/METADATA
automate_graphite_feeder-0.9.1.dist-info/WHEEL
automate_graphite_feeder-0.9.1.dist-info/top_level.txt
automate_graphite_feeder-0.9.1.dist-info/RECORD
