Metadata-Version: 2.1
Name: automate-graphite-feeder
Version: 0.9.1
Summary: A simple way to enrich with graphics the web interface for the automate-home projects
Home-page: https://github.com/majamassarini/automate-home
Author: Maja Massarini
Author-email: maja.massarini@gmail.com
License: MIT
Platform: UNKNOWN
Classifier: Development Status :: 3 - Alpha
Classifier: License :: OSI Approved :: MIT License
Classifier: Operating System :: POSIX :: Linux
Classifier: Programming Language :: Python :: 3.8
Classifier: Topic :: Internet :: WWW/HTTP :: HTTP Servers
Classifier: Intended Audience :: Developers
License-File: COPYING
Requires-Dist: automate-home
